mvi/__init__.py
mvi/communication.py
mvi/data_types.py
mvi/exceptions.py
mvi/notebook.py
mvi/testing.py
mvi/utilities.py
mvi/_service/__init__.py
mvi/_service/db.py
mvi/_service/logger.py
mvi/_service/monitoring_api.py
mvi/_service/service.py
mvi/cli/__init__.py
mvi/cli/cli.py
mvi/cli/cliutils.py
mvi/cli/config.py
mvi/cli/mvi_template/README.md
mvi/cli/mvi_template/cookiecutter.json
mvi/cli/mvi_template/hooks/pre_gen_project.py
mvi/cli/mvi_template/{{cookiecutter.project_name}}/.s2iignore
mvi/cli/mvi_template/{{cookiecutter.project_name}}/README.md
mvi/cli/mvi_template/{{cookiecutter.project_name}}/requirements.txt
mvi/cli/mvi_template/{{cookiecutter.project_name}}/service.py
mvi/cli/mvi_template/{{cookiecutter.project_name}}/.s2i/environment
mvi/cli/mvi_template/{{cookiecutter.project_name}}/tests/base_functionality_test.py
mvi/cli/mvi_template/{{cookiecutter.project_name}}/tests/user_test.py
va_mvi-0.4.5.dist-info/METADATA
va_mvi-0.4.5.dist-info/WHEEL
va_mvi-0.4.5.dist-info/entry_points.txt
va_mvi-0.4.5.dist-info/top_level.txt
va_mvi-0.4.5.dist-info/RECORD
