Metadata-Version: 2.1
Name: va-mvi
Version: 0.4.5
Summary: Multiviz Integrator SDK and command-line interface
Home-page: https://github.com/vikinganalytics/mvi
Author: Viking Analytics
Author-email: info@vikinganalytics.se
License: LICENSE
Platform: UNKNOWN
Classifier: Programming Language :: Python :: 3
Classifier: Operating System :: OS Independent
Requires-Python: >=3.6
Requires-Dist: typer
Requires-Dist: tabulate
Requires-Dist: cookiecutter
Requires-Dist: uvicorn
Requires-Dist: requests
Requires-Dist: fastapi
Requires-Dist: pydantic
Requires-Dist: numpy
Requires-Dist: setuptools
Requires-Dist: sqlalchemy
Requires-Dist: aiofiles
Requires-Dist: pytest
Requires-Dist: pandas
